pyartifacts/__init__.py
pyartifacts/artifact.py
pyartifacts/artifact_schema.json
pyartifacts/definitions.py
pyartifacts/registry.py
pyartifacts/variables.py
pyartifacts-0.12.5.dist-info/LICENSE
pyartifacts-0.12.5.dist-info/METADATA
pyartifacts-0.12.5.dist-info/WHEEL
pyartifacts-0.12.5.dist-info/top_level.txt
pyartifacts-0.12.5.dist-info/RECORD
